flippers/__about__.py
flippers/__init__.py
flippers/_typing.py
flippers/_core/__init__.py
flippers/_core/_core.py
flippers/lfs/__init__.py
flippers/lfs/_lfs.py
flippers/models/__init__.py
flippers/models/_base.py
flippers/models/_snorkel.py
flippers-0.0.1b5.dist-info/METADATA
flippers-0.0.1b5.dist-info/WHEEL
flippers-0.0.1b5.dist-info/licenses/LICENSE
flippers-0.0.1b5.dist-info/RECORD
