Metadata-Version: 2.3
Name: flippers
Version: 0.0.1b5
Summary: `flippers` is a weak supervision library for creating high quality labels using domain kownledge and heuristics.
Project-URL: Documentation, https://github.com/liamtoran/flippers#readme
Project-URL: Issues, https://github.com/liamtoran/flippers/issues
Project-URL: Source, https://github.com/liamtoran/flippers
Author-email: Liam Toran <liam.toran@gmail.com>
License-Expression: Apache-2.0
License-File: LICENSE
Keywords: annotation,data,data labeling,data science,labeling,machine learning,weak supervision
Classifier: Development Status :: 4 - Beta
Classifier: Programming Language :: Python
Classifier: Programming Language :: Python :: 3.7
Classifier: Programming Language :: Python :: 3.8
Classifier: Programming Language :: Python :: 3.9
Classifier: Programming Language :: Python :: 3.10
Classifier: Programming Language :: Python :: 3.11
Requires-Python: >=3.7
Requires-Dist: numpy
Requires-Dist: pandas
Requires-Dist: scikit-learn<1.4.0
Requires-Dist: torch
Requires-Dist: tqdm
